[
  {
    "model": "auth.group",
    "pk": 1,
    "fields": {
      "name": "MANAGER_GENERAL"
    }
  },
  {
    "model": "auth.group",
    "pk": 2,
    "fields": {
      "name": "MANAGER_INSTITUTION"
    }
  },
  {
    "model": "auth.group",
    "pk": 3,
    "fields": {
      "name": "MANAGER_MISC"
    }
  },
  {
    "model": "auth.group",
    "pk": 4,
    "fields": {
      "name": "COMMISSION"
    }
  },
  {
    "model": "auth.group",
    "pk": 5,
    "fields": {
      "name": "STUDENT_INSTITUTION"
    }
  },
  {
    "model": "auth.group",
    "pk": 6,
    "fields": {
      "name": "STUDENT_MISC"
    }
  }
]
